chonktxt/__init__.py
chonktxt/chonktxt.py
chonktxt-0.1.1.dist-info/METADATA
chonktxt-0.1.1.dist-info/WHEEL
chonktxt-0.1.1.dist-info/top_level.txt
chonktxt-0.1.1.dist-info/RECORD
