Metadata-Version: 2.1
Name: chonktxt
Version: 0.1.1
Summary: An SDK that makes it easy to do contextual chunking
Home-page: https://github.com/cjinghong/chonktxt
Author: Jing Hong
Author-email: Jing Hong <jinghongchan@gmail.com>
Project-URL: homepage, https://github.com/cjinghong/chonktxt
Classifier: Programming Language :: Python :: 3
Classifier: License :: OSI Approved :: MIT License
Classifier: Operating System :: OS Independent
Requires-Python: >=3.6
Requires-Dist: anthropic
Requires-Dist: pdfminer.six
Requires-Dist: tqdm
